{
  "kind": "singleType",
  "collectionName": "home_pages",
  "info": {
    "singularName": "home-page",
    "pluralName": "home-pages",
    "displayName": "Home Page",
    "description": ""
  },
  "options": {
    "draftAndPublish": true
  },
  "pluginOptions": {},
  "attributes": {
    "blocks": {
      "type": "dynamiczone",
      "components": [
        "block.banner",
        "block.company-logo",
        "block.service",
        "block.proposal",
        "block.case-studies",
        "block.working-process",
        "block.team",
        "block.testimonial",
        "block.contact-us"
      ]
    }
  }
}
